Metadata-Version: 2.1
Name: tvims
Version: 0.0.15
Summary: Aboubakar
Home-page: 
Author: tak0ysebe
Author-email: ffmarkov@yandex.ru
License: MIT
Keywords: test
Classifier: Development Status :: 5 - Production/Stable
Classifier: Intended Audience :: Education
Classifier: Operating System :: Microsoft :: Windows :: Windows 10
Classifier: License :: OSI Approved :: MIT License
Classifier: Programming Language :: Python :: 3
License-File: LICENSE.txt
